genomicshelper/__init__.py
genomicshelper/g_Log.py
genomicshelper/g_Protocol.py
genomicshelper/g_init.py
genomicshelper/ghelp.py
genomicshelper/r_run.py
genomicshelper/s_script.py
genomicshelper/t_add_template.py
genomicshelper/t_copy_template.py
genomicshelper/t_load_header.py
genomicshelper/t_load_template.py
genomicshelper/t_parse_template.py
genomicshelper/t_print_template.py
genomicshelper/t_search_template.py
genomicshelper/template/0_template
genomicshelper/template/0_template_py
genomicshelper/template/admixture.tmp
genomicshelper/template/admixture_cv.tmp
genomicshelper/template/apptainer.tmp
genomicshelper/template/apt.tmp
genomicshelper/template/apt_get.tmp
genomicshelper/template/awk_replace.tmp
genomicshelper/template/awk_split.tmp
genomicshelper/template/bash.header
genomicshelper/template/bcf2bed.tmp
genomicshelper/template/bcf2vcf.tmp
genomicshelper/template/bcf_contig.tmp
genomicshelper/template/bcf_filter.tmp
genomicshelper/template/bcf_format.tmp
genomicshelper/template/bcf_header.tmp
genomicshelper/template/bcf_info.tmp
genomicshelper/template/bcf_meta.tmp
genomicshelper/template/bcf_samples.tmp
genomicshelper/template/bcf_stats.tmp
genomicshelper/template/bcf_vars.tmp
genomicshelper/template/bcftools_view.tmp
genomicshelper/template/bed2bgen.tmp
genomicshelper/template/bed2pgen.tmp
genomicshelper/template/bed2vcf.tmp
genomicshelper/template/brew.tmp
genomicshelper/template/chmod_onlyowner.tmp
genomicshelper/template/chmod_readonly.tmp
genomicshelper/template/conda_env.tmp
genomicshelper/template/conda_env_py.tmp
genomicshelper/template/conda_env_r.tmp
genomicshelper/template/csv2tsv.tmp
genomicshelper/template/curl.tmp
genomicshelper/template/deploy_github_page.tmp
genomicshelper/template/docker_pull.tmp
genomicshelper/template/eig2bed.tmp
genomicshelper/template/eigenstrat2ped.tmp
genomicshelper/template/excel2tsv.tmp
genomicshelper/template/export.tmp
genomicshelper/template/fastqc.tmp
genomicshelper/template/for.tmp
genomicshelper-0.0.3.dist-info/licenses/LICENSE
genomicshelper-0.0.3.dist-info/METADATA
genomicshelper-0.0.3.dist-info/WHEEL
genomicshelper-0.0.3.dist-info/entry_points.txt
genomicshelper-0.0.3.dist-info/top_level.txt
genomicshelper-0.0.3.dist-info/RECORD
